k_judgment_gate/__init__.py
k_judgment_gate/gate.py
k_judgment_gate/roles.py
k_judgment_gate/schema.py
k_judgment_gate/scope.py
k_judgment_gate/stemmer.py
k_judgment_gate/telemetry.py
k_judgment_gate-1.2.1.dist-info/licenses/LICENSE
k_judgment_gate-1.2.1.dist-info/METADATA
k_judgment_gate-1.2.1.dist-info/WHEEL
k_judgment_gate-1.2.1.dist-info/top_level.txt
k_judgment_gate-1.2.1.dist-info/RECORD
