Metadata-Version: 2.4
Name: k-judgment-gate
Version: 1.2.1
Summary: Governance-first judgment detection for Korean LLM systems. NOT a filter.
Author: k-judgment-gate Contributors
License: Apache-2.0
Project-URL: Homepage, https://github.com/Nick-heo-eg/k-judgment-gate
Project-URL: Documentation, https://github.com/Nick-heo-eg/k-judgment-gate#readme
Project-URL: Repository, https://github.com/Nick-heo-eg/k-judgment-gate
Project-URL: Issues, https://github.com/Nick-heo-eg/k-judgment-gate/issues
Keywords: judgment,governance,korean,llm,oversight
Classifier: Development Status :: 3 - Alpha
Classifier: Intended Audience :: Developers
Classifier: License :: OSI Approved :: Apache Software License
Classifier: Programming Language :: Python :: 3
Classifier: Programming Language :: Python :: 3.9
Classifier: Programming Language :: Python :: 3.10
Classifier: Programming Language :: Python :: 3.11
Classifier: Programming Language :: Python :: 3.12
Requires-Python: >=3.9
License-File: LICENSE
Dynamic: license-file
